<?xml version = '1.0' encoding = 'UTF-8'?>
<Relation class="oracle.dbtools.crest.model.design.logical.Relation" name="Relation_15" directorySegmentName="seg_0" id="7051EC92-DA8A-2235-BA1B-3858967FBA16">
<createdBy>eduardo</createdBy>
<createdTime>2021-01-02 17:02:36 UTC</createdTime>
<ownerDesignName>CentroDeDatos</ownerDesignName>
<engineerTo>
<item key="87C3B845-8339-BA7B-65E2-F381A957A53F" value="true"/>
</engineerTo>
<sourcePk>5F313E8A-2DA8-40EA-81C9-5D13C978E733</sourcePk>
<identifying>false</identifying>
<optionalSource>false</optionalSource>
<optionalTarget>false</optionalTarget>
<sourceCardinality>1</sourceCardinality>
<sourceEntity>A8019872-26F3-543B-C4F1-6FDA0904804F</sourceEntity>
<targetCardinalityString>*</targetCardinalityString>
<targetEntity>2C1B1938-FDB4-8CF6-F89A-0B5261800F17</targetEntity>
<transferable>true</transferable>
<deleteRule>NO ACTION</deleteRule>
</Relation>
